mhealthdata/__init__.py
mhealthdata/dataloader.py
mhealthdata/offset.py
mhealthdata/utils.py
mhealthdata-0.0.3.dist-info/LICENSE
mhealthdata-0.0.3.dist-info/METADATA
mhealthdata-0.0.3.dist-info/WHEEL
mhealthdata-0.0.3.dist-info/top_level.txt
mhealthdata-0.0.3.dist-info/RECORD
