Metadata-Version: 2.1
Name: mhealthdata
Version: 0.0.3
Summary: Wearable health data to NumPy
Home-page: https://github.com/timpyrkov/mhealthdata
Author: Tim Pyrkov
Author-email: tim.pyrkov@gmail.com
License: MIT License
Platform: UNKNOWN
Classifier: Programming Language :: Python :: 3
Classifier: License :: OSI Approved :: MIT License
Classifier: Topic :: Scientific/Engineering
Requires-Python: >=3.8
License-File: LICENSE
Requires-Dist: numpy
Requires-Dist: pandas
Requires-Dist: tqdm
